{
  "nodes": [

    {"id": "", "group": 0, "big": 1},
    {"id": "Language", "group": 1, "big": 1},
    {"id": "Tool", "group": 2, "big": 1},
    {"id": "Frontend", "group": 3, "big": 1},
    {"id": "DevOps", "group": 4, "big": 1},
    {"id": "Backend", "group": 5, "big": 1},
    {"id": "DataOps", "group": 7, "big": 1},
    {"id": "Blockchain", "group": 8, "big": 1},

    {"id": "Rust", "group": 1, "extra":"love"},
    {"id": "Python", "group": 1, "extra":"love"},
    {"id": "WebAssembly", "group": 1},
    {"id": "JavaScript+TypeScript", "group": 1},
    {"id": "Scheme", "group": 1},
    {"id": "Lisp", "group": 1},
    {"id": "Solidity", "group": 1},
    {"id": "Motoko", "group": 1, "extra":"love"},
    {"id": "Dart", "group": 1},
    {"id": "Bash", "group": 1},
    {"id": "SQL", "group": 1},

    {"id": "Flask", "group": 5},
    {"id": "Firebase", "group": 5},
    {"id": "Postgraphile", "group": 5},
    {"id": "FastAPI", "group": 5},
    {"id": "Express", "group": 5},
    {"id": "Node.js", "group": 5},

    {"id": "Flutter", "group": 3, "extra":"love"},
    {"id": "Tokio", "group": 9},
    {"id": "Serde", "group": 9},
    {"id": "Nuxt", "group": 3},
    {"id": "React", "group": 3},
    {"id": "Svelte", "group": 3},
    {"id": "Pydantic", "group": 9},
    {"id": "Pytest", "group": 9},
    {"id": "Pandas", "group": 7, "extra":"love"},
    {"id": "Numpy", "group": 7},
    {"id": "Plotly", "group": 3},
    {"id": "Dash", "group": 3},
    {"id": "Matplotlib/Seaborn", "group": 3},

    {"id": "Linux", "group": 2, "extra":"love"},
    {"id": "git", "group": 2, "extra":"love"},
    {"id": "Jupyter", "group": 2, "extra":"love"},
    {"id": "Arch", "group": 2, "extra":"love"},
    {"id": "Guix", "group": 2, "extra":"love"},
    {"id": "Nix", "group": 2, "extra":"love"},
    {"id": "Emacs", "group": 2, "extra":"love"},
    {"id": "Vim", "group": 2},
    {"id": "VSCode", "group": 2},

    {"id": "Kubernetes", "group": 4},
    {"id": "Docker", "group": 4},
    {"id": "GitHub Actions", "group": 4},
    {"id": "GitLab CI/CD", "group": 4},
    {"id": "Azure", "group": 4},
    {"id": "Azure Functions", "group": 4},
    {"id": "Azure DevOps", "group": 4},
    {"id": "Azure Kubernetes Service", "group": 4},
    {"id": "Google Cloud", "group": 4},
    {"id": "Google Cloud Functions", "group": 4},

    {"id": "Google Pub/Sub", "group": 7},
    {"id": "BigQuery", "group": 7},
    {"id": "MongoDB", "group": 7},
    {"id": "SQLAlchemy", "group": 7},
    {"id": "Postgres", "group": 7},
    {"id": "GraphQL", "group": 7, "extra":"love"},
    {"id": "REST API/Open API", "group": 7},
    {"id": "Airflow", "group": 7},
    {"id": "Dgraph", "group": 7},

    {"id": "Binance Smart Chain", "group": 8},
    {"id": "Ethereum", "group": 8},
    {"id": "Chainlink", "group": 8},
    {"id": "Internet Computer", "group": 8, "extra":"love"},
    {"id": "Brownie", "group": 8},
    {"id": "Ganache", "group": 8},
    {"id": "IPSF & Pinana", "group": 8},
    {"id": "Infura", "group": 8},
    {"id": "OpenZepplin", "group": 8},
    {"id": "Aave", "group": 8},
    {"id": "ERC721 (NFT)", "group": 8},
    {"id": "ERC20 (Token)", "group": 8},
    {"id": "Web3.py", "group": 8}
    

  ],
  "links": [

    {"source": "Tool", "target": "Emacs", "value": 1},
    {"source": "Tool", "target": "VSCode", "value": 1},
    {"source": "Tool", "target": "Vim", "value": 1},
    {"source": "Tool", "target": "Linux", "value": 1},
    {"source": "Tool", "target": "Docker", "value": 1},
    {"source": "Tool", "target": "Jupyter", "value": 1},
    {"source": "Tool", "target": "git", "value": 1},

    {"source": "DevOps", "target": "Azure", "value": 1},
    {"source": "DevOps", "target": "Google Cloud", "value": 1},
    {"source": "DevOps", "target": "Kubernetes", "value": 1},
    {"source": "DevOps", "target": "Docker", "value": 1},
    {"source": "DevOps", "target": "GitHub Actions", "value": 1},
    {"source": "DevOps", "target": "GitLab CI/CD", "value": 1},

      {"source": "Azure", "target": "Azure Functions", "value": 1},
      {"source": "Azure", "target": "Azure Kubernetes Service", "value": 1},
      {"source": "Azure", "target": "Azure DevOps", "value": 1},

      {"source": "Google Cloud", "target": "Firebase", "value": 1},
      {"source": "Google Cloud", "target": "BigQuery", "value": 1},
      {"source": "Google Cloud", "target": "Google Cloud Functions", "value": 1},
      {"source": "Google Cloud", "target": "Google Pub/Sub", "value": 1},

    {"source": "Backend", "target": "FastAPI", "value": 1},
    {"source": "Backend", "target": "Flask", "value": 1},
    {"source": "Backend", "target": "Postgraphile", "value": 1},
    {"source": "Backend", "target": "Express", "value": 1},
    {"source": "Node.js", "target": "Express", "value": 1},
    {"source": "Node.js", "target": "Postgraphile", "value": 1},
    {"source": "Express", "target": "Postgraphile", "value": 1},
    {"source": "React", "target": "Postgraphile", "value": 1},
    {"source": "Backend", "target": "Firebase", "value": 1},

    {"source": "Language", "target": "Python", "value": 1},
    {"source": "Language", "target": "JavaScript+TypeScript", "value": 9},
    {"source": "Language", "target": "Rust", "value": 1},
    {"source": "Language", "target": "Dart", "value": 1},
    {"source": "Language", "target": "Bash", "value": 1},
    {"source": "Language", "target": "SQL", "value": 1},
    {"source": "Language", "target": "Scheme", "value": 1},
    {"source": "Language", "target": "Lisp", "value": 1},
    {"source": "Language", "target": "Solidity", "value": 1},
    {"source": "Language", "target": "Motoko", "value": 1},
    {"source": "Rust", "target": "WebAssembly", "value": 1},
    {"source": "Rust", "target": "Serde", "value": 1},
    {"source": "Rust", "target": "Tokio", "value": 1},
    {"source": "WebAssembly", "target": "JavaScript+TypeScript", "value": 1},

    {"source": "DataOps", "target": "Airflow", "value": 1},
    {"source": "DataOps", "target": "BigQuery", "value": 1},
    {"source": "DataOps", "target": "Pandas", "value": 1},
    {"source": "DataOps", "target": "Numpy", "value": 1},
    {"source": "DataOps", "target": "Plotly", "value": 1},
    {"source": "Plotly", "target": "Dash", "value": 1},
    {"source": "Dash", "target": "Flask", "value": 1},
    {"source": "DataOps", "target": "SQL", "value": 1},
    {"source": "DataOps", "target": "Postgres", "value": 1},
    {"source": "Postgraphile", "target": "Postgres", "value": 1},
    {"source": "DataOps", "target": "Airflow", "value": 1},
    {"source": "DataOps", "target": "MongoDB", "value": 1},
    {"source": "DataOps", "target": "Firebase", "value": 1},
    {"source": "DataOps", "target": "Dgraph", "value": 1},
    {"source": "DataOps", "target": "GraphQL", "value": 1},
    {"source": "DataOps", "target": "REST API/Open API", "value": 1},
    {"source": "DataOps", "target": "Google Pub/Sub", "value": 1},

    {"source": "Blockchain", "target": "Internet Computer", "value": 1},
    {"source": "Blockchain", "target": "Ethereum", "value": 1},

    {"source": "Frontend", "target": "React", "value": 1},
    {"source": "Frontend", "target": "Flutter", "value": 1},
    {"source": "Frontend", "target": "Nuxt", "value": 1},
    {"source": "Frontend", "target": "Svelte", "value": 1},
    {"source": "Frontend", "target": "Dash", "value": 1},
    {"source": "Frontend", "target": "Plotly", "value": 1},
    {"source": "Frontend", "target": "Matplotlib/Seaborn", "value": 1},
    {"source": "JavaScript+TypeScript", "target": "Svelte", "value": 1},
    {"source": "Dart", "target": "Flutter", "value": 1},
    {"source": "Flutter", "target": "Firebase", "value": 1},
    {"source": "JavaScript+TypeScript", "target": "Express", "value": 1},
    {"source": "JavaScript+TypeScript", "target": "Nuxt", "value": 1},
    {"source": "JavaScript+TypeScript", "target": "React", "value": 1},
    {"source": "JavaScript+TypeScript", "target": "Node.js", "value": 1},
    {"source": "JavaScript+TypeScript", "target": "Postgraphile", "value": 1},

    {"source": "Python", "target": "Pandas", "value": 1},
    {"source": "Python", "target": "Numpy", "value": 1},
    {"source": "Python", "target": "Plotly", "value": 1},
    {"source": "Python", "target": "Dash", "value": 1},
    {"source": "Python", "target": "Matplotlib/Seaborn", "value": 1},
    {"source": "Python", "target": "Airflow", "value": 1},
    {"source": "Python", "target": "Web3.py", "value": 1},
    {"source": "Python", "target": "Brownie", "value": 1},
    {"source": "Python", "target": "Pytest", "value": 1},
    {"source": "Python", "target": "Pydantic", "value": 1},
    {"source": "FastAPI", "target": "Pydantic", "value": 1},
    {"source": "Python", "target": "SQLAlchemy", "value": 1},
    {"source": "DataOps", "target": "SQLAlchemy", "value": 1},
    {"source": "Python", "target": "Flask", "value": 1},
    {"source": "Python", "target": "FastAPI", "value": 1},

    {"source": "Solidity", "target": "Ethereum", "value": 1},
    {"source": "Web3.py", "target": "Ethereum", "value": 1},
    {"source": "Brownie", "target": "Ethereum", "value": 1},
    {"source": "Ethereum", "target": "Binance Smart Chain", "value": 1},
    {"source": "Ethereum", "target": "Chainlink", "value": 1},
    {"source": "Ethereum", "target": "Ganache", "value": 1},
    {"source": "Ethereum", "target": "Infura", "value": 1},
    {"source": "Ethereum", "target": "OpenZepplin", "value": 1},
    {"source": "Ethereum", "target": "Aave", "value": 1},
    {"source": "Ethereum", "target": "ERC721 (NFT)", "value": 1},
    {"source": "Ethereum", "target": "ERC20 (Token)", "value": 1},
    {"source": "Blockchain", "target": "IPSF & Pinana", "value": 1},
    {"source": "Motoko", "target": "Internet Computer", "value": 1},
    {"source": "Rust", "target": "Internet Computer", "value": 1},
    
    {"source": "GraphQL", "target": "Postgraphile", "value": 1},
    {"source": "GraphQL", "target": "Dgraph", "value": 1},

    {"source": "Linux", "target": "Arch", "value": 1},
    {"source": "Lisp", "target": "Emacs", "value": 1},
    {"source": "Linux", "target": "Guix", "value": 1},
    {"source": "Guix", "target": "Scheme", "value": 1},
    {"source": "Linux", "target": "Nix", "value": 1},
    {"source": "Linux", "target": "Bash", "value": 1},
    {"source": "Tool", "target": "Bash", "value": 1},
    {"source": "Kubernetes", "target": "Azure Kubernetes Service", "value": 1},


    {"source": "JavaScript+TypeScript", "target": "Node.js", "value": 1},
    {"source": "JavaScript+TypeScript", "target": "Postgraphile", "value": 1},
    {"source": "JavaScript+TypeScript", "target": "React", "value": 1},
    {"source": "JavaScript+TypeScript", "target": "Svelte", "value": 1},
    {"source": "JavaScript+TypeScript", "target": "Plotly", "value": 1}

  ]
}
